youtubeSpotifyConverter/__init__.py
youtubeSpotifyConverter/youtubeSpotifyConverter.py
youtubeSpotifyConverter-0.2.0.dist-info/LICENSE
youtubeSpotifyConverter-0.2.0.dist-info/METADATA
youtubeSpotifyConverter-0.2.0.dist-info/WHEEL
youtubeSpotifyConverter-0.2.0.dist-info/top_level.txt
youtubeSpotifyConverter-0.2.0.dist-info/RECORD
