Metadata-Version: 2.1
Name: youtubeSpotifyConverter
Version: 0.2.0
Summary: Convert between Spotify, YouTube and YouTube Music URLs
License: MIT
License-File: LICENSE
Requires-Dist: requests
